polychromos/__init__.py
polychromos/easing.py
polychromos/palette.py
polychromos/py.typed
polychromos/color/__init__.py
polychromos/color/color.py
polychromos/color/web.py
polychromos-1.4.1.dist-info/METADATA
polychromos-1.4.1.dist-info/WHEEL
polychromos-1.4.1.dist-info/licenses/LICENSE
polychromos-1.4.1.dist-info/RECORD
