Metadata-Version: 2.4
Name: polychromos
Version: 1.4.1
Project-URL: Homepage, https://gitlab.com/Kencho1/polychromos
Project-URL: Repository, https://gitlab.com/Kencho1/polychromos
Project-URL: Issues, https://gitlab.com/Kencho1/polychromos/-/issues
Project-URL: Changelog, https://gitlab.com/Kencho1/polychromos/-/blob/main/CHANGELOG.md
Author: Jesús Alonso Abad
License-Expression: MIT
License-File: LICENSE
Classifier: Development Status :: 5 - Production/Stable
Classifier: License :: OSI Approved :: MIT License
Classifier: Natural Language :: English
Classifier: Operating System :: OS Independent
Classifier: Programming Language :: Python :: 3
Classifier: Programming Language :: Python :: 3 :: Only
Classifier: Programming Language :: Python :: 3.11
Classifier: Programming Language :: Python :: 3.12
Classifier: Programming Language :: Python :: 3.13
Classifier: Programming Language :: Python :: 3.14
Classifier: Topic :: Artistic Software
Classifier: Topic :: Multimedia :: Graphics
Classifier: Topic :: Scientific/Engineering :: Visualization
Classifier: Typing :: Typed
Requires-Python: >=3.11
Provides-Extra: test
Requires-Dist: mypy~=1.8; extra == 'test'
Requires-Dist: pytest-cov~=4.0; extra == 'test'
Requires-Dist: pytest~=7.0; extra == 'test'
Requires-Dist: ruff~=0.8; extra == 'test'
